pyshark_plus_plus/__init__.py
pyshark_plus_plus/exceptions.py
pyshark_plus_plus/pyshark_plus_plus.py
pyshark_plus_plus/statistics.py
pyshark_plus_plus-1.0.0rc3.dist-info/LICENSE.txt
pyshark_plus_plus-1.0.0rc3.dist-info/METADATA
pyshark_plus_plus-1.0.0rc3.dist-info/WHEEL
pyshark_plus_plus-1.0.0rc3.dist-info/top_level.txt
pyshark_plus_plus-1.0.0rc3.dist-info/RECORD
